gridspeccer/__init__.py
gridspeccer/aux.py
gridspeccer/cli.py
gridspeccer/core.py
gridspeccer/defaults/matplotlibrc
gridspeccer/defaults/tex_matplotlibrc
Gridspeccer-0.2.2.dist-info/AUTHORS.md
Gridspeccer-0.2.2.dist-info/LICENSE
Gridspeccer-0.2.2.dist-info/METADATA
Gridspeccer-0.2.2.dist-info/WHEEL
Gridspeccer-0.2.2.dist-info/entry_points.txt
Gridspeccer-0.2.2.dist-info/top_level.txt
Gridspeccer-0.2.2.dist-info/zip-safe
Gridspeccer-0.2.2.dist-info/RECORD
